
{
  "header": {
    "reportVersion": 1,
    "event": "Allocation failed - JavaScript heap out of memory",
    "trigger": "FatalError",
    "filename": "report.20220207.183659.5132.0.001.json",
    "dumpEventTime": "2022-02-07T18:36:59Z",
    "dumpEventTimeStamp": "1644239219920",
    "processId": 5132,
    "cwd": "D:\\reactproject\\Ecommerce pro\\frontend",
    "commandLine": [
      "C:\\Program Files\\nodejs\\node.exe",
      "D:\\reactproject\\Ecommerce pro\\frontend\\node_modules\\react-scripts\\scripts\\build.js"
    ],
    "nodejsVersion": "v12.14.0",
    "wordSize": 32,
    "arch": "ia32",
    "platform": "win32",
    "componentVersions": {
      "node": "12.14.0",
      "v8": "7.7.299.13-node.16",
      "uv": "1.33.1",
      "zlib": "1.2.11",
      "brotli": "1.0.7",
      "ares": "1.15.0",
      "modules": "72",
      "nghttp2": "1.39.2",
      "napi": "5",
      "llhttp": "1.1.4",
      "http_parser": "2.8.0",
      "openssl": "1.1.1d",
      "cldr": "35.1",
      "icu": "64.2",
      "tz": "2019c",
      "unicode": "12.1"
    },
    "release": {
      "name": "node",
      "lts": "Erbium",
      "headersUrl": "https://nodejs.org/download/release/v12.14.0/node-v12.14.0-headers.tar.gz",
      "sourceUrl": "https://nodejs.org/download/release/v12.14.0/node-v12.14.0.tar.gz",
      "libUrl": "https://nodejs.org/download/release/v12.14.0/win-x86/node.lib"
    },
    "osName": "Windows_NT",
    "osRelease": "6.1.7601",
    "osVersion": "Windows 7 Ultimate Service Pack 1",
    "osMachine": "i686",
    "cpus": [
      {
        "model": "Intel(R) Core(TM) i3 CPU       M 370  @ 2.40GHz",
        "speed": 2394,
        "user": 2793104,
        "nice": 0,
        "sys": 1341889,
        "idle": 7819721,
        "irq": 30919
      },
      {
        "model": "Intel(R) Core(TM) i3 CPU       M 370  @ 2.40GHz",
        "speed": 2394,
        "user": 3504890,
        "nice": 0,
        "sys": 1252516,
        "idle": 7196513,
        "irq": 63149
      },
      {
        "model": "Intel(R) Core(TM) i3 CPU       M 370  @ 2.40GHz",
        "speed": 2394,
        "user": 1628510,
        "nice": 0,
        "sys": 834230,
        "idle": 9491054,
        "irq": 67486
      },
      {
        "model": "Intel(R) Core(TM) i3 CPU       M 370  @ 2.40GHz",
        "speed": 2394,
        "user": 1209428,
        "nice": 0,
        "sys": 483447,
        "idle": 10260794,
        "irq": 55739
      }
    ],
    "networkInterfaces": [
      {
        "name": "Wireless Network Connection",
        "internal": false,
        "mac": "5c:ac:4c:53:8c:65",
        "address": "2401:4900:5232:ff4d:c00b:1f21:b1c3:cead",
        "netmask": "ffff:ffff:ffff:ffff::",
        "family": "IPv6",
        "scopeid": 0
      },
      {
        "name": "Wireless Network Connection",
        "internal": false,
        "mac": "5c:ac:4c:53:8c:65",
        "address": "2401:4900:5232:ff4d:59d2:7a95:5fdd:db70",
        "netmask": "ffff:ffff:ffff:ffff:ffff:ffff:ffff:ffff",
        "family": "IPv6",
        "scopeid": 0
      },
      {
        "name": "Wireless Network Connection",
        "internal": false,
        "mac": "5c:ac:4c:53:8c:65",
        "address": "fe80::c00b:1f21:b1c3:cead",
        "netmask": "ffff:ffff:ffff:ffff::",
        "family": "IPv6",
        "scopeid": 12
      },
      {
        "name": "Wireless Network Connection",
        "internal": false,
        "mac": "5c:ac:4c:53:8c:65",
        "address": "192.168.43.32",
        "netmask": "255.255.255.0",
        "family": "IPv4"
      },
      {
        "name": "Loopback Pseudo-Interface 1",
        "internal": true,
        "mac": "00:00:00:00:00:00",
        "address": "::1",
        "netmask": "ffff:ffff:ffff:ffff:ffff:ffff:ffff:ffff",
        "family": "IPv6",
        "scopeid": 0
      },
      {
        "name": "Loopback Pseudo-Interface 1",
        "internal": true,
        "mac": "00:00:00:00:00:00",
        "address": "127.0.0.1",
        "netmask": "255.0.0.0",
        "family": "IPv4"
      }
    ],
    "host": "Dell-PC"
  },
  "javascriptStack": {
    "message": "No stack.",
    "stack": [
      "Unavailable."
    ]
  },
  "nativeStack": [
  ],
  "javascriptHeap": {
    "totalMemory": 504844288,
    "totalCommittedMemory": 504844288,
    "usedMemory": 490646748,
    "availableMemory": 15071792,
    "memoryLimit": 512753664,
    "heapSpaces": {
      "read_only_space": {
        "memorySize": 262144,
        "committedMemory": 262144,
        "capacity": 262008,
        "used": 22100,
        "available": 239908
      },
      "new_space": {
        "memorySize": 3145728,
        "committedMemory": 3145728,
        "capacity": 1572048,
        "used": 378764,
        "available": 1193284
      },
      "old_space": {
        "memorySize": 371789824,
        "committedMemory": 371789824,
        "capacity": 365741636,
        "used": 361584460,
        "available": 4157176
      },
      "code_space": {
        "memorySize": 1736704,
        "committedMemory": 1736704,
        "capacity": 1483040,
        "used": 1483040,
        "available": 0
      },
      "map_space": {
        "memorySize": 4460544,
        "committedMemory": 4460544,
        "capacity": 4025720,
        "used": 4025720,
        "available": 0
      },
      "large_object_space": {
        "memorySize": 122859520,
        "committedMemory": 122859520,
        "capacity": 122639448,
        "used": 122639448,
        "available": 0
      },
      "code_large_object_space": {
        "memorySize": 589824,
        "committedMemory": 589824,
        "capacity": 513216,
        "used": 513216,
        "available": 0
      },
      "new_large_object_space": {
        "memorySize": 0,
        "committedMemory": 0,
        "capacity": 1572048,
        "used": 0,
        "available": 1572048
      }
    }
  },
  "resourceUsage": {
    "userCpuSeconds": 377.85,
    "kernelCpuSeconds": 24.663,
    "cpuConsumptionPercent": 161.005,
    "maxRss": 533549056,
    "pageFaults": {
      "IORequired": 556597,
      "IONotRequired": 0
    },
    "fsActivity": {
      "reads": 7528,
      "writes": 973
    }
  },
  "libuv": [
  ],
  "environmentVariables": {
    "ALLUSERSPROFILE": "C:\\ProgramData",
    "APPDATA": "C:\\Users\\Dell\\AppData\\Roaming",
    "BABEL_ENV": "production",
    "CHROME_CRASHPAD_PIPE_NAME": "\\\\.\\pipe\\crashpad_6040_NVQYBSCADMBWMZFU",
    "COLORTERM": "truecolor",
    "CommonProgramFiles": "C:\\Program Files\\Common Files",
    "COMPUTERNAME": "DELL-PC",
    "ComSpec": "C:\\Windows\\system32\\cmd.exe",
    "dp0": "D:\\reactproject\\Ecommerce pro\\frontend\\node_modules\\.bin\\",
    "FP_NO_HOST_CHECK": "NO",
    "HOME": "C:\\Users\\Dell",
    "HOMEDRIVE": "C:",
    "HOMEPATH": "\\Users\\Dell",
    "INIT_CWD": "D:\\reactproject\\Ecommerce pro\\frontend",
    "LANG": "en_US.UTF-8",
    "LOCALAPPDATA": "C:\\Users\\Dell\\AppData\\Local",
    "LOGONSERVER": "\\\\DELL-PC",
    "NODE": "C:\\Program Files\\nodejs\\node.exe",
    "NODE_ENV": "production",
    "NODE_EXE": "C:\\Program Files\\nodejs\\\\node.exe",
    "NODE_PATH": "",
    "NPM_CLI_JS": "C:\\Program Files\\nodejs\\\\node_modules\\npm\\bin\\npm-cli.js",
    "npm_config_access": "",
    "npm_config_allow_same_version": "",
    "npm_config_also": "",
    "npm_config_always_auth": "",
    "npm_config_argv": "{\"remain\":[],\"cooked\":[\"run\",\"build\"],\"original\":[\"run\",\"build\"]}",
    "npm_config_audit": "true",
    "npm_config_audit_level": "low",
    "npm_config_auth_type": "legacy",
    "npm_config_before": "",
    "npm_config_bin_links": "true",
    "npm_config_browser": "",
    "npm_config_ca": "",
    "npm_config_cache": "C:\\Users\\Dell\\AppData\\Roaming\\npm-cache",
    "npm_config_cache_lock_retries": "10",
    "npm_config_cache_lock_stale": "60000",
    "npm_config_cache_lock_wait": "10000",
    "npm_config_cache_max": "Infinity",
    "npm_config_cache_min": "10",
    "npm_config_cafile": "",
    "npm_config_cert": "",
    "npm_config_cidr": "",
    "npm_config_color": "true",
    "npm_config_commit_hooks": "true",
    "npm_config_depth": "Infinity",
    "npm_config_description": "true",
    "npm_config_dev": "",
    "npm_config_dry_run": "",
    "npm_config_editor": "notepad.exe",
    "npm_config_engine_strict": "",
    "npm_config_fetch_retries": "2",
    "npm_config_fetch_retry_factor": "10",
    "npm_config_fetch_retry_maxtimeout": "60000",
    "npm_config_fetch_retry_mintimeout": "10000",
    "npm_config_force": "",
    "npm_config_format_package_lock": "true",
    "npm_config_fund": "true",
    "npm_config_git": "git",
    "npm_config_git_tag_version": "true",
    "npm_config_global": "",
    "npm_config_globalconfig": "C:\\Users\\Dell\\AppData\\Roaming\\npm\\etc\\npmrc",
    "npm_config_globalignorefile": "C:\\Users\\Dell\\AppData\\Roaming\\npm\\etc\\npmignore",
    "npm_config_global_style": "",
    "npm_config_group": "",
    "npm_config_ham_it_up": "",
    "npm_config_heading": "npm",
    "npm_config_https_proxy": "",
    "npm_config_if_present": "",
    "npm_config_ignore_prepublish": "",
    "npm_config_ignore_scripts": "",
    "npm_config_init_author_email": "",
    "npm_config_init_author_name": "",
    "npm_config_init_author_url": "",
    "npm_config_init_license": "ISC",
    "npm_config_init_module": "C:\\Users\\Dell\\.npm-init.js",
    "npm_config_init_version": "1.0.0",
    "npm_config_json": "",
    "npm_config_key": "",
    "npm_config_legacy_bundling": "",
    "npm_config_link": "",
    "npm_config_local_address": "",
    "npm_config_loglevel": "notice",
    "npm_config_logs_max": "10",
    "npm_config_long": "",
    "npm_config_maxsockets": "50",
    "npm_config_message": "%s",
    "npm_config_metrics_registry": "https://registry.npmjs.org/",
    "npm_config_node_gyp": "C:\\Program Files\\nodejs\\node_modules\\npm\\node_modules\\node-gyp\\bin\\node-gyp.js",
    "npm_config_node_options": "",
    "npm_config_node_version": "12.14.0",
    "npm_config_noproxy": "",
    "npm_config_offline": "",
    "npm_config_onload_script": "",
    "npm_config_only": "",
    "npm_config_optional": "true",
    "npm_config_otp": "",
    "npm_config_package_lock": "true",
    "npm_config_package_lock_only": "",
    "npm_config_parseable": "",
    "npm_config_prefer_offline": "",
    "npm_config_prefer_online": "",
    "npm_config_prefix": "C:\\Users\\Dell\\AppData\\Roaming\\npm",
    "npm_config_preid": "",
    "npm_config_production": "",
    "npm_config_progress": "true",
    "npm_config_proxy": "",
    "npm_config_read_only": "",
    "npm_config_rebuild_bundle": "true",
    "npm_config_registry": "https://registry.npmjs.org/",
    "npm_config_rollback": "true",
    "npm_config_save": "true",
    "npm_config_save_bundle": "",
    "npm_config_save_dev": "",
    "npm_config_save_exact": "",
    "npm_config_save_optional": "",
    "npm_config_save_prefix": "^",
    "npm_config_save_prod": "",
    "npm_config_scope": "",
    "npm_config_scripts_prepend_node_path": "warn-only",
    "npm_config_script_shell": "",
    "npm_config_searchexclude": "",
    "npm_config_searchlimit": "20",
    "npm_config_searchopts": "",
    "npm_config_searchstaleness": "900",
    "npm_config_send_metrics": "",
    "npm_config_shell": "C:\\Windows\\system32\\cmd.exe",
    "npm_config_shrinkwrap": "true",
    "npm_config_sign_git_commit": "",
    "npm_config_sign_git_tag": "",
    "npm_config_sso_poll_frequency": "500",
    "npm_config_sso_type": "oauth",
    "npm_config_strict_ssl": "true",
    "npm_config_tag": "latest",
    "npm_config_tag_version_prefix": "v",
    "npm_config_timing": "",
    "npm_config_tmp": "C:\\Users\\Dell\\AppData\\Local\\Temp",
    "npm_config_umask": "0000",
    "npm_config_unicode": "",
    "npm_config_unsafe_perm": "true",
    "npm_config_update_notifier": "true",
    "npm_config_usage": "",
    "npm_config_user": "",
    "npm_config_userconfig": "C:\\Users\\Dell\\.npmrc",
    "npm_config_user_agent": "npm/6.13.4 node/v12.14.0 win32 ia32",
    "npm_config_version": "",
    "npm_config_versions": "",
    "npm_config_viewer": "browser",
    "npm_execpath": "C:\\Program Files\\nodejs\\node_modules\\npm\\bin\\npm-cli.js",
    "npm_lifecycle_event": "build",
    "npm_lifecycle_script": "react-scripts build",
    "npm_node_execpath": "C:\\Program Files\\nodejs\\node.exe",
    "npm_package_browserslist_development_0": "last 1 chrome version",
    "npm_package_browserslist_development_1": "last 1 firefox version",
    "npm_package_browserslist_development_2": "last 1 safari version",
    "npm_package_browserslist_production_0": ">0.2%",
    "npm_package_browserslist_production_1": "not dead",
    "npm_package_browserslist_production_2": "not op_mini all",
    "npm_package_dependencies_axios": "^0.21.1",
    "npm_package_dependencies_chart_js": "^3.5.1",
    "npm_package_dependencies_country_state_city": "^3.0.1",
    "npm_package_dependencies_overlay_navbar": "^1.0.4",
    "npm_package_dependencies_react": "^17.0.2",
    "npm_package_dependencies_react_alert": "^7.0.3",
    "npm_package_dependencies_react_alert_template_basic": "^1.0.2",
    "npm_package_dependencies_react_chartjs_2": "^3.0.4",
    "npm_package_dependencies_react_dom": "^17.0.2",
    "npm_package_dependencies_react_helmet": "^6.1.0",
    "npm_package_dependencies_react_icons": "^4.2.0",
    "npm_package_dependencies_react_js_pagination": "^3.0.3",
    "npm_package_dependencies_react_material_ui_carousel": "^2.3.1",
    "npm_package_dependencies_react_redux": "^7.2.4",
    "npm_package_dependencies_react_router_dom": "^5.2.0",
    "npm_package_dependencies_react_scripts": "4.0.3",
    "npm_package_dependencies_redux": "^4.1.1",
    "npm_package_dependencies_redux_devtools_extension": "^2.13.9",
    "npm_package_dependencies_redux_thunk": "^2.3.0",
    "npm_package_dependencies_webfontloader": "^1.6.28",
    "npm_package_dependencies_web_vitals": "^1.1.2",
    "npm_package_dependencies__material_ui_core": "^4.12.3",
    "npm_package_dependencies__material_ui_data_grid": "^4.0.0-alpha.37",
    "npm_package_dependencies__material_ui_icons": "^4.11.2",
    "npm_package_dependencies__material_ui_lab": "^4.0.0-alpha.60",
    "npm_package_dependencies__stripe_react_stripe_js": "^1.4.1",
    "npm_package_dependencies__stripe_stripe_js": "^1.17.1",
    "npm_package_dependencies__testing_library_jest_dom": "^5.14.1",
    "npm_package_dependencies__testing_library_react": "^11.2.7",
    "npm_package_dependencies__testing_library_user_event": "^12.8.3",
    "npm_package_description": "This project was bootstrapped with [Create React App](https://github.com/facebook/create-react-app).",
    "npm_package_eslintConfig_extends_0": "react-app",
    "npm_package_eslintConfig_extends_1": "react-app/jest",
    "npm_package_name": "frontend",
    "npm_package_private": "true",
    "npm_package_proxy": "http://192.168.43.32:4000",
    "npm_package_readmeFilename": "README.md",
    "npm_package_scripts_build": "react-scripts build",
    "npm_package_scripts_eject": "react-scripts eject",
    "npm_package_scripts_start": "react-scripts --max_old_space_size=1026 start",
    "npm_package_scripts_test": "react-scripts test",
    "npm_package_version": "0.1.0",
    "NPM_PREFIX_NPM_CLI_JS": "C:\\Users\\Dell\\AppData\\Roaming\\npm\\node_modules\\npm\\bin\\npm-cli.js",
    "NUMBER_OF_PROCESSORS": "4",
    "ORIGINAL_XDG_CURRENT_DESKTOP": "undefined",
    "OS": "Windows_NT",
    "Path": "C:\\Program Files\\nodejs\\node_modules\\npm\\node_modules\\npm-lifecycle\\node-gyp-bin;D:\\reactproject\\Ecommerce pro\\frontend\\node_modules\\.bin;C:\\Windows\\system32;C:\\Windows;C:\\Windows\\System32\\Wbem;C:\\Windows\\System32\\WindowsPowerShell\\v1.0\\;C:\\Program Files\\nodejs\\;;C:\\Users\\Dell\\AppData\\Local\\Programs\\Microsoft VS Code\\bin;C:\\Users\\Dell\\AppData\\Roaming\\npm;C:\\Program Files\\MongoDB\\Server\\3.2\\bin",
    "PATHEXT": ".COM;.EXE;.BAT;.CMD;.VBS;.VBE;.JSE;.WSF;.WSH;.MSC",
    "PROCESSOR_ARCHITECTURE": "x86",
    "PROCESSOR_IDENTIFIER": "x86 Family 6 Model 37 Stepping 5, GenuineIntel",
    "PROCESSOR_LEVEL": "6",
    "PROCESSOR_REVISION": "2505",
    "ProgramData": "C:\\ProgramData",
    "ProgramFiles": "C:\\Program Files",
    "PROMPT": "$P$G",
    "PSModulePath": "C:\\Users\\Dell\\Documents\\WindowsPowerShell\\Modules;C:\\Windows\\system32\\WindowsPowerShell\\v1.0\\Modules\\",
    "PUBLIC": "C:\\Users\\Public",
    "SESSIONNAME": "Console",
    "SystemDrive": "C:",
    "SystemRoot": "C:\\Windows",
    "TEMP": "C:\\Users\\Dell\\AppData\\Local\\Temp",
    "TERM_PROGRAM": "vscode",
    "TERM_PROGRAM_VERSION": "1.64.0",
    "TMP": "C:\\Users\\Dell\\AppData\\Local\\Temp",
    "USERDOMAIN": "Dell-PC",
    "USERNAME": "Dell",
    "USERPROFILE": "C:\\Users\\Dell",
    "windir": "C:\\Windows",
    "windows_tracing_flags": "3",
    "windows_tracing_logfile": "C:\\BVTBin\\Tests\\installpackage\\csilogfile.log",
    "_prog": "node"
  },
  "sharedObjects": [
    "C:\\Program Files\\nodejs\\node.exe",
    "C:\\Windows\\SYSTEM32\\ntdll.dll",
    "C:\\Program Files\\AVAST Software\\Avast\\aswhook.dll",
    "C:\\Windows\\system32\\kernel32.dll",
    "C:\\Windows\\system32\\KERNELBASE.dll",
    "C:\\Windows\\system32\\dbghelp.dll",
    "C:\\Windows\\system32\\msvcrt.dll",
    "C:\\Windows\\system32\\WS2_32.dll",
    "C:\\Windows\\system32\\RPCRT4.dll",
    "C:\\Windows\\system32\\NSI.dll",
    "C:\\Windows\\system32\\ADVAPI32.dll",
    "C:\\Windows\\SYSTEM32\\sechost.dll",
    "C:\\Windows\\system32\\USER32.dll",
    "C:\\Windows\\system32\\GDI32.dll",
    "C:\\Windows\\system32\\LPK.dll",
    "C:\\Windows\\system32\\USP10.dll",
    "C:\\Windows\\system32\\IPHLPAPI.DLL",
    "C:\\Windows\\system32\\WINNSI.DLL",
    "C:\\Windows\\system32\\PSAPI.DLL",
    "C:\\Windows\\system32\\USERENV.dll",
    "C:\\Windows\\system32\\profapi.dll",
    "C:\\Windows\\system32\\CRYPT32.dll",
    "C:\\Windows\\system32\\MSASN1.dll",
    "C:\\Windows\\system32\\bcrypt.dll",
    "C:\\Windows\\system32\\WINMM.dll",
    "C:\\Windows\\system32\\IMM32.DLL",
    "C:\\Windows\\system32\\MSCTF.dll",
    "C:\\Windows\\system32\\api-ms-win-core-synch-l1-2-0.DLL",
    "C:\\Windows\\system32\\powrprof.dll",
    "C:\\Windows\\system32\\SETUPAPI.dll",
    "C:\\Windows\\system32\\CFGMGR32.dll",
    "C:\\Windows\\system32\\OLEAUT32.dll",
    "C:\\Windows\\system32\\ole32.dll",
    "C:\\Windows\\system32\\DEVOBJ.dll",
    "C:\\Windows\\system32\\uxtheme.dll",
    "C:\\Windows\\system32\\mswsock.dll",
    "C:\\Windows\\System32\\wshtcpip.dll",
    "C:\\Windows\\System32\\wship6.dll",
    "C:\\Windows\\system32\\bcryptprimitives.dll",
    "C:\\Windows\\system32\\apphelp.dll",
    "C:\\Windows\\system32\\dhcpcsvc.DLL",
    "C:\\Windows\\system32\\dhcpcsvc6.DLL",
    "C:\\Windows\\system32\\NLAapi.dll",
    "C:\\Windows\\system32\\napinsp.dll",
    "C:\\Windows\\system32\\pnrpnsp.dll",
    "C:\\Windows\\system32\\DNSAPI.dll",
    "C:\\Windows\\System32\\winrnr.dll"
  ]
}